smsc_client/__init__.py
smsc_client/categories.py
smsc_client/api/__init__.py
smsc_client/api/abc.py
smsc_client/api/api.py
smsc_client/base/__init__.py
smsc_client/base/category.py
smsc_client/methods/__init__.py
smsc_client/methods/default.py
smsc_client-0.0.1.dist-info/METADATA
smsc_client-0.0.1.dist-info/WHEEL
smsc_client-0.0.1.dist-info/top_level.txt
smsc_client-0.0.1.dist-info/RECORD
